pybolt/__init__.py
pybolt/utils.py
pybolt/bolt_nlp/__init__.py
pybolt/bolt_nlp/count_ngrams
pybolt/bolt_nlp/count_ngrams.py
pybolt/bolt_nlp/gray_encode.py
pybolt/bolt_nlp/tfidf.py
pybolt/bolt_nlp/tokenizer.py
pybolt/bolt_nlp/word2vec.py
pybolt/bolt_nlp/word_discover.py
pybolt/bolt_nlp/words_tagging.py
pybolt/bolt_nlp/char_cnn_classification/__init__.py
pybolt/bolt_nlp/char_cnn_classification/model.py
pybolt/bolt_nlp/finalseg/__init__.py
pybolt/bolt_nlp/finalseg/prob_emit.py
pybolt/bolt_nlp/finalseg/prob_start.py
pybolt/bolt_nlp/finalseg/prob_trans.py
pybolt/bolt_nlp/naive_bayes_classification/__init__.py
pybolt/bolt_nlp/naive_bayes_classification/bernoulliNB.py
pybolt/bolt_nlp/naive_bayes_classification/utils.py
pybolt/bolt_speedup/__init__.py
pybolt/bolt_text/__init__.py
pybolt/bolt_text/bolt_text.py
pybolt/bolt_text/char_clean.py
pybolt/bolt_text/prefix_set.py
pybolt/data/char_project.txt
pybolt/data/zi_pinyin.txt
py_bolt-0.0.24.dist-info/LICENSE
py_bolt-0.0.24.dist-info/METADATA
py_bolt-0.0.24.dist-info/WHEEL
py_bolt-0.0.24.dist-info/top_level.txt
py_bolt-0.0.24.dist-info/RECORD
