Metadata-Version: 2.1
Name: py-bolt
Version: 0.0.24
Summary: Fast text processing acceleration.
Home-page: https://github.com/mikuh/pybolt
Author: geb
Author-email: 853934146@qq.com
License: UNKNOWN
Platform: UNKNOWN
Classifier: Programming Language :: Python :: 3
Classifier: License :: OSI Approved :: MIT License
Classifier: Operating System :: OS Independent
Requires-Python: >=3.6
Requires-Dist: numpy
Requires-Dist: pandas
Requires-Dist: pandarallel
